{"duration":4593,"records":[{"duration":1744,"stepId":"io.quarkus.vertx.http.deployment.devmode.console.DevConsoleProcessor#setupDeploymentSideHandling","started":"19:49:51.677","dependents":[373,371,372],"id":370,"thread":"build-14"},{"duration":1596,"stepId":"io.quarkus.hibernate.orm.deployment.HibernateOrmProcessor#enhancerDomainObjects","started":"19:49:50.631","dependents":[367,366,368],"id":365,"thread":"build-22"},{"duration":707,"stepId":"io.quarkus.arc.deployment.ArcProcessor#generateResources","started":"19:49:50.814","dependents":[346,356,375,355,343,342,341,363,373,368,344,345,376],"id":340,"thread":"build-26"},{"duration":637,"stepId":"io.quarkus.deployment.steps.MainClassBuildStep#build","started":"19:49:53.422","dependents":[],"id":376,"thread":"build-8"},{"duration":504,"stepId":"io.quarkus.hibernate.orm.deployment.HibernateOrmProcessor#pregenProxies","started":"19:49:52.676","dependents":[376],"id":369,"thread":"build-26"},{"duration":453,"stepId":"io.quarkus.deployment.steps.ConfigGenerationBuildStep#generateConfigClass","started":"19:49:50.812","dependents":[375],"id":339,"thread":"build-16"},{"duration":446,"stepId":"io.quarkus.deployment.index.ApplicationArchiveBuildStep#build","started":"19:49:49.748","dependents":[291,224,366,221,279,368,226,230,330,235,222,223],"id":220,"thread":"build-26"},{"duration":443,"stepId":"io.quarkus.deployment.steps.ClassTransformingBuildStep#handleClassTransformation","started":"19:49:52.233","dependents":[369],"id":368,"thread":"build-8"},{"duration":284,"stepId":"io.quarkus.deployment.steps.ConfigDescriptionBuildStep#createConfigDescriptions","started":"19:49:49.636","dependents":[306,370],"id":218,"thread":"build-5"},{"duration":232,"stepId":"io.quarkus.deployment.console.ConsoleProcessor#setupConsole","started":"19:49:49.690","dependents":[290,219,221,217],"id":216,"thread":"build-2"},{"duration":227,"stepId":"io.quarkus.arc.deployment.ArcProcessor#registerBeans","started":"19:49:50.398","dependents":[317,315,316,326,311,324,312,323,318,313,319,314,325],"id":310,"thread":"build-26"},{"duration":152,"stepId":"io.quarkus.hibernate.orm.deployment.HibernateOrmProcessor#parsePersistenceXmlDescriptors","started":"19:49:49.737","dependents":[279,212,210],"id":209,"thread":"build-1"},{"duration":149,"stepId":"io.quarkus.narayana.jta.deployment.NarayanaJtaProcessor#build","started":"19:49:49.764","dependents":[291,375,301,376],"id":215,"thread":"build-20"},{"duration":133,"stepId":"io.quarkus.deployment.logging.LoggingResourceProcessor#setupLoggingRuntimeInit","started":"19:49:50.218","dependents":[290,370,309,376,298],"id":289,"thread":"build-26"},{"duration":127,"stepId":"io.quarkus.vertx.http.deployment.VertxHttpProcessor#bodyHandler","started":"19:49:49.772","dependents":[376,363],"id":213,"thread":"build-16"},{"duration":124,"stepId":"io.quarkus.arc.deployment.ArcProcessor#validate","started":"19:49:50.683","dependents":[340,338,334,368,331,332,333,329,335,330,336],"id":328,"thread":"build-1"},{"duration":110,"stepId":"io.quarkus.resteasy.reactive.jackson.deployment.processor.ResteasyReactiveJacksonProcessor#jsonDefault","started":"19:49:49.628","dependents":[346],"id":111,"thread":"build-4"},{"duration":108,"stepId":"io.quarkus.datasource.deployment.devservices.DevUIDatasourceProcessor#devConsoleCleanDatabaseHandler","started":"19:49:49.495","dependents":[370,309,376],"id":45,"thread":"build-3"},{"duration":105,"stepId":"io.quarkus.vertx.core.deployment.VertxCoreProcessor#createVertxThreadFactory","started":"19:49:49.501","dependents":[195,376],"id":46,"thread":"build-6"},{"duration":103,"stepId":"io.quarkus.vertx.http.deployment.webjar.WebJarProcessor#processWebJarDevMode","started":"19:49:49.752","dependents":[309,376],"id":204,"thread":"build-14"},{"duration":102,"stepId":"io.quarkus.resteasy.reactive.server.deployment.ResteasyReactiveProcessor#setupEndpoints","started":"19:49:51.522","dependents":[368,347,354,356,375,376,353,348],"id":346,"thread":"build-16"},{"duration":99,"stepId":"io.quarkus.deployment.console.ConsoleProcessor#quitCommand","started":"19:49:49.500","dependents":[350],"id":42,"thread":"build-4"},{"duration":98,"stepId":"io.quarkus.resteasy.reactive.server.deployment.ResteasyReactiveProcessor#vertxIntegration","started":"19:49:49.628","dependents":[355,352,353],"id":106,"thread":"build-1"},{"duration":97,"stepId":"io.quarkus.deployment.steps.ApplicationIndexBuildStep#build","started":"19:49:49.644","dependents":[317,346,301,121,220],"id":120,"thread":"build-13"},{"duration":97,"stepId":"io.quarkus.deployment.ide.IdeProcessor#detectRunningIdeProcesses","started":"19:49:49.630","dependents":[107],"id":105,"thread":"build-7"},{"duration":87,"stepId":"io.quarkus.agroal.deployment.AgroalProcessor#build","started":"19:49:49.769","dependents":[308,208,322,375,207,206],"id":205,"thread":"build-8"},{"duration":87,"stepId":"io.quarkus.mutiny.deployment.MutinyProcessor#buildTimeInit","started":"19:49:49.805","dependents":[376],"id":211,"thread":"build-7"},{"duration":84,"stepId":"io.quarkus.deployment.logging.LoggingResourceProcessor#logConsoleCommand","started":"19:49:49.630","dependents":[350],"id":103,"thread":"build-10"},{"duration":78,"stepId":"io.quarkus.hibernate.orm.deployment.HibernateOrmProcessor#defineJpaEntities","started":"19:49:50.207","dependents":[283,287,279,369,275,344,288,375,365,284,285,276],"id":274,"thread":"build-28"},{"duration":69,"stepId":"io.quarkus.vertx.http.deployment.VertxHttpProcessor#preinitializeRouter","started":"19:49:49.831","dependents":[361,325,324,323,376],"id":214,"thread":"build-18"},{"duration":66,"stepId":"io.quarkus.vertx.http.deployment.devmode.console.DevConsoleProcessor#collectTemplates","started":"19:49:49.737","dependents":[370],"id":184,"thread":"build-10"},{"duration":64,"stepId":"io.quarkus.reactive.pg.client.deployment.ReactivePgClientProcessor#config","started":"19:49:49.749","dependents":[322],"id":136,"thread":"build-3"},{"duration":64,"stepId":"io.quarkus.deployment.steps.BannerProcessor#recordBanner","started":"19:49:49.771","dependents":[289,376],"id":201,"thread":"build-17"},{"duration":63,"stepId":"io.quarkus.vertx.http.deployment.devmode.tests.TestsProcessor#runFailedTests","started":"19:49:49.773","dependents":[370,309],"id":202,"thread":"build-4"},{"duration":53,"stepId":"io.quarkus.deployment.steps.ThreadPoolSetup#createExecutor","started":"19:49:49.771","dependents":[199,196,198,376,363,200],"id":195,"thread":"build-9"},{"duration":49,"stepId":"io.quarkus.vertx.core.deployment.VertxCoreProcessor#eventLoopCount","started":"19:49:49.771","dependents":[374,321,376],"id":194,"thread":"build-11"},{"duration":45,"stepId":"io.quarkus.vertx.http.deployment.HttpSecurityProcessor#initBasicAuth","started":"19:49:49.770","dependents":[325,324,323,376],"id":193,"thread":"build-22"},{"duration":43,"stepId":"io.quarkus.datasource.deployment.DataSourcesExcludedFromHealthChecksProcessor#produceBean","started":"19:49:49.766","dependents":[325,324,323,376],"id":189,"thread":"build-24"},{"duration":43,"stepId":"io.quarkus.vertx.http.deployment.HttpSecurityProcessor#initMtlsClientAuth","started":"19:49:49.764","dependents":[325,324,323,376],"id":185,"thread":"build-25"},{"duration":41,"stepId":"io.quarkus.deployment.logging.LoggingResourceProcessor#registerMetrics","started":"19:49:49.704","dependents":[289,376],"id":104,"thread":"build-6"},{"duration":40,"stepId":"io.quarkus.arc.deployment.devconsole.ArcDevConsoleProcessor#exposeArcContainer","started":"19:49:49.646","dependents":[372,376],"id":93,"thread":"build-15"},{"duration":40,"stepId":"io.quarkus.resteasy.reactive.server.deployment.ResteasyReactiveScanningProcessor#handleCustomAnnotatedMethods","started":"19:49:50.215","dependents":[291,273,272,301],"id":271,"thread":"build-16"},{"duration":40,"stepId":"io.quarkus.arc.deployment.BeanArchiveProcessor#build","started":"19:49:50.317","dependents":[319,292,296,293,346,356,301,318,294,297,342,353],"id":291,"thread":"build-22"},{"duration":40,"stepId":"io.quarkus.vertx.http.deployment.HttpSecurityProcessor#initFormAuth","started":"19:49:49.769","dependents":[361,357,325,370,324,323,376],"id":191,"thread":"build-19"},{"duration":39,"stepId":"io.quarkus.hibernate.orm.deployment.HibernateOrmProcessor#setupPersistenceProvider","started":"19:49:49.769","dependents":[197,344,376],"id":190,"thread":"build-23"},{"duration":39,"stepId":"io.quarkus.deployment.dev.IsolatedDevModeMain$5$1@154de324","started":"19:49:49.743","dependents":[346,301],"id":182,"thread":"build-13"},{"duration":39,"stepId":"io.quarkus.vertx.http.deployment.HttpSecurityProcessor#setupAuthenticationMechanisms","started":"19:49:49.768","dependents":[291,340,301,376,363],"id":187,"thread":"build-28"},{"duration":38,"stepId":"io.quarkus.devservices.postgresql.deployment.PostgresqlDevServicesProcessor#setupPostgres","started":"19:49:49.501","dependents":[290],"id":32,"thread":"build-8"},{"duration":38,"stepId":"io.quarkus.vertx.http.deployment.VertxHttpProcessor#cors","started":"19:49:49.769","dependents":[376,363],"id":186,"thread":"build-27"},{"duration":38,"stepId":"io.quarkus.arc.deployment.devconsole.ArcDevConsoleProcessor#collectBeanInfo","started":"19:49:50.808","dependents":[362],"id":338,"thread":"build-14"},{"duration":35,"stepId":"io.quarkus.vertx.http.deployment.devmode.ArcDevProcessor#invocationsEndpoint","started":"19:49:49.567","dependents":[370,309,376],"id":43,"thread":"build-8"},{"duration":34,"stepId":"io.quarkus.vertx.core.deployment.VertxCoreProcessor#ioThreadDetector","started":"19:49:49.773","dependents":[192,376],"id":188,"thread":"build-18"},{"duration":33,"stepId":"io.quarkus.resteasy.reactive.server.deployment.ResteasyReactiveProcessor#serverSerializers","started":"19:49:51.631","dependents":[356,375,376],"id":355,"thread":"build-16"},{"duration":30,"stepId":"io.quarkus.deployment.console.ConsoleProcessor#helpCommand","started":"19:49:49.572","dependents":[350],"id":44,"thread":"build-1"},{"duration":29,"stepId":"io.quarkus.arc.deployment.SyntheticBeansProcessor#initRegular","started":"19:49:50.642","dependents":[326],"id":325,"thread":"build-14"},{"duration":29,"stepId":"io.quarkus.arc.deployment.ArcProcessor#initialize","started":"19:49:50.362","dependents":[338,310,304],"id":301,"thread":"build-5"},{"duration":27,"stepId":"io.quarkus.arc.deployment.SyntheticBeansProcessor#initRuntime","started":"19:49:50.642","dependents":[373,326,371,372,376],"id":324,"thread":"build-1"},{"duration":23,"stepId":"io.quarkus.hibernate.orm.deployment.HibernateOrmProcessor#configurationDescriptorBuilding","started":"19:49:50.285","dependents":[280,282,283,287,281,369,308,288,286,376,284,285],"id":279,"thread":"build-8"},{"duration":23,"stepId":"io.quarkus.netty.deployment.NettyProcessor#setNettyMachineId","started":"19:49:49.774","dependents":[376],"id":183,"thread":"build-15"},{"duration":22,"stepId":"io.quarkus.vertx.http.deployment.devmode.console.DevConsoleProcessor#setupDevConsoleRoutes","started":"19:49:50.400","dependents":[361,357,370,376],"id":309,"thread":"build-5"},{"duration":20,"stepId":"io.quarkus.vertx.deployment.VertxProcessor#autoAddScope","started":"19:49:49.610","dependents":[297],"id":66,"thread":"build-6"},{"duration":20,"stepId":"io.quarkus.vertx.http.deployment.devmode.console.ConfigEditorProcessor#config","started":"19:49:50.380","dependents":[370,309,350,372,376],"id":306,"thread":"build-14"},{"duration":19,"stepId":"io.quarkus.deployment.steps.ConfigGenerationBuildStep#runtimeDefaultsConfig","started":"19:49:50.388","dependents":[308],"id":307,"thread":"build-2"},{"duration":19,"stepId":"io.quarkus.smallrye.context.deployment.SmallRyeContextPropagationProcessor#buildStatic","started":"19:49:49.743","dependents":[376],"id":158,"thread":"build-15"},{"duration":18,"stepId":"io.quarkus.hibernate.orm.deployment.HibernateOrmProcessor#build_c156fff69640ec926378717b8035fab8ad639e43","started":"19:49:50.309","dependents":[340,376],"id":288,"thread":"build-11"},{"duration":17,"stepId":"io.quarkus.jsonp.deployment.JsonpProcessor#build","started":"19:49:49.525","dependents":[375,376],"id":33,"thread":"build-1"},{"duration":17,"stepId":"io.quarkus.deployment.DockerStatusProcessor#IsDockerWorking","started":"19:49:49.744","dependents":[290,302],"id":156,"thread":"build-6"},{"duration":16,"stepId":"io.quarkus.hibernate.orm.deployment.metrics.HibernateOrmMetricsProcessor#metrics","started":"19:49:49.811","dependents":[376],"id":197,"thread":"build-18"},{"duration":16,"stepId":"io.quarkus.hibernate.orm.deployment.HibernateOrmCdiProcessor#registerAnnotations","started":"19:49:49.500","dependents":[291,169,301],"id":28,"thread":"build-1"},{"duration":15,"stepId":"io.quarkus.arc.deployment.ArcProcessor#loggerProducer","started":"19:49:49.743","dependents":[291,301],"id":154,"thread":"build-4"},{"duration":14,"stepId":"io.quarkus.vertx.http.deployment.devmode.tests.TestsProcessor#setupTestRoutes","started":"19:49:49.696","dependents":[361,357,370,217,376],"id":102,"thread":"build-15"},{"duration":13,"stepId":"io.quarkus.deployment.dev.HotDeploymentWatchedFileBuildStep#setupWatchedFileHotDeployment","started":"19:49:50.312","dependents":[373,371,372],"id":287,"thread":"build-2"},{"duration":13,"stepId":"io.quarkus.deployment.steps.CompiledJavaVersionBuildStep#compiledJavaVersion","started":"19:49:49.747","dependents":[346],"id":157,"thread":"build-8"},{"duration":13,"stepId":"io.quarkus.deployment.steps.ConfigGenerationBuildStep#checkForBuildTimeConfigChange","started":"19:49:50.352","dependents":[376],"id":298,"thread":"build-2"},{"duration":13,"stepId":"io.quarkus.deployment.dev.testing.TestTracingProcessor#testConsoleCommand","started":"19:49:50.206","dependents":[350],"id":270,"thread":"build-8"},{"duration":12,"stepId":"io.quarkus.vertx.http.deployment.HttpSecurityProcessor#builtins","started":"19:49:49.636","dependents":[291,301,187],"id":84,"thread":"build-11"},{"duration":12,"stepId":"io.quarkus.deployment.steps.ReflectiveHierarchyStep#build","started":"19:49:51.628","dependents":[375],"id":354,"thread":"build-26"},{"duration":12,"stepId":"io.quarkus.vertx.http.deployment.VertxHttpProcessor#frameworkRoot","started":"19:49:49.695","dependents":[361,101,370,102,309,336,363,348],"id":95,"thread":"build-12"},{"duration":12,"stepId":"io.quarkus.resteasy.reactive.server.deployment.ResteasyReactiveScanningProcessor#cacheControlSupport","started":"19:49:49.737","dependents":[346],"id":137,"thread":"build-14"},{"duration":11,"stepId":"io.quarkus.vertx.http.deployment.devmode.ArcDevProcessor#eventsEndpoint","started":"19:49:49.744","dependents":[370,309,376],"id":151,"thread":"build-20"},{"duration":11,"stepId":"io.quarkus.deployment.steps.DevServicesConfigBuildStep#setup","started":"19:49:50.378","dependents":[307,300,373,306,302,305,371,372],"id":299,"thread":"build-26"},{"duration":10,"stepId":"io.quarkus.vertx.http.deployment.devmode.console.DevConsoleProcessor#setupConsole","started":"19:49:49.696","dependents":[373,371,372],"id":101,"thread":"build-14"},{"duration":10,"stepId":"io.quarkus.resteasy.reactive.server.deployment.ResteasyReactiveCDIProcessor#contextInjection","started":"19:49:49.561","dependents":[291,295,301,297],"id":38,"thread":"build-1"},{"duration":10,"stepId":"io.quarkus.devservices.deployment.DevServicesProcessor#config","started":"19:49:50.382","dependents":[350,303],"id":302,"thread":"build-16"},{"duration":10,"stepId":"io.quarkus.hibernate.orm.deployment.HibernateOrmProcessor#addPersistenceUnitAnnotationToIndex","started":"19:49:49.744","dependents":[224],"id":149,"thread":"build-19"},{"duration":9,"stepId":"io.quarkus.agroal.deployment.AgroalProcessor#generateDataSourceSupportBean","started":"19:49:49.856","dependents":[291,325,324,301,323,376],"id":208,"thread":"build-14"},{"duration":9,"stepId":"io.quarkus.arc.deployment.ArcProcessor#registerSyntheticObservers","started":"19:49:50.672","dependents":[340,327,328,375],"id":326,"thread":"build-1"},{"duration":9,"stepId":"io.quarkus.resteasy.reactive.server.deployment.ResteasyReactiveProcessor#setupDeployment","started":"19:49:51.664","dependents":[361,357,360,370,375,376],"id":356,"thread":"build-26"},{"duration":8,"stepId":"io.quarkus.vertx.http.deployment.VertxHttpProcessor#finalizeRouter","started":"19:49:51.676","dependents":[364,373,371,372,376],"id":363,"thread":"build-8"},{"duration":8,"stepId":"io.quarkus.arc.deployment.SplitPackageProcessor#splitPackageDetection","started":"19:49:50.194","dependents":[340],"id":226,"thread":"build-18"},{"duration":8,"stepId":"io.quarkus.narayana.jta.deployment.NarayanaJtaProcessor#unremovableBean","started":"19:49:49.748","dependents":[328],"id":153,"thread":"build-24"},{"duration":8,"stepId":"io.quarkus.reactive.pg.client.deployment.ReactivePgClientProcessor#build","started":"19:49:50.633","dependents":[373,325,322,371,324,372,323,376],"id":321,"thread":"build-5"},{"duration":8,"stepId":"io.quarkus.vertx.http.deployment.devmode.console.DevConsoleProcessor#handler","started":"19:49:49.636","dependents":[289,309,376],"id":80,"thread":"build-2"},{"duration":7,"stepId":"io.quarkus.hibernate.orm.deployment.HibernateOrmCdiProcessor#generateDataSourceBeans","started":"19:49:50.310","dependents":[291,325,324,301,323,376],"id":286,"thread":"build-5"},{"duration":7,"stepId":"io.quarkus.hibernate.orm.deployment.HibernateOrmProcessor#registerBeans","started":"19:49:50.309","dependents":[291,328,301],"id":285,"thread":"build-22"},{"duration":7,"stepId":"io.quarkus.resteasy.reactive.server.deployment.ResteasyReactiveScanningProcessor#defaultUnwrappedException","started":"19:49:49.748","dependents":[273],"id":150,"thread":"build-25"},{"duration":7,"stepId":"io.quarkus.netty.deployment.NettyProcessor#registerQualifiers","started":"19:49:49.525","dependents":[291,301],"id":30,"thread":"build-10"},{"duration":7,"stepId":"io.quarkus.vertx.http.deployment.devmode.console.DevConsoleProcessor#setupWebJar","started":"19:49:49.743","dependents":[204],"id":138,"thread":"build-7"},{"duration":7,"stepId":"io.quarkus.deployment.steps.CombinedIndexBuildStep#build","started":"19:49:50.195","dependents":[269,229,349,227,301,264,228,276,251,225,354,247,259,246,271,249,253,265,231,232,279,250,311,248,313,367,240,267,258,233,255,239,238,366,254,234,237,235,236,285,270,241,334,273,242,244,277,263,243],"id":224,"thread":"build-20"},{"duration":7,"stepId":"io.quarkus.vertx.core.deployment.VertxCoreProcessor#build_9d6b7122fb368970c50c3a870d1f672392cd8afb","started":"19:49:49.744","dependents":[308,322,375],"id":144,"thread":"build-17"},{"duration":7,"stepId":"io.quarkus.agroal.deployment.AgroalProcessor#generateDataSourceBeans","started":"19:49:49.856","dependents":[279,325,344,324,323,210,286,376],"id":207,"thread":"build-9"},{"duration":7,"stepId":"io.quarkus.resteasy.reactive.server.deployment.ResteasyReactiveScanningProcessor#compressionSupport","started":"19:49:49.689","dependents":[346],"id":94,"thread":"build-14"},{"duration":7,"stepId":"io.quarkus.vertx.core.deployment.VertxCoreProcessor#createVertxContextHandlers","started":"19:49:49.748","dependents":[198,195,376],"id":148,"thread":"build-23"},{"duration":6,"stepId":"io.quarkus.deployment.logging.LoggingResourceProcessor#setupLoggingStaticInit","started":"19:49:49.638","dependents":[376],"id":79,"thread":"build-9"},{"duration":6,"stepId":"io.quarkus.datasource.deployment.devservices.DevUIDatasourceProcessor#devConsoleInfo","started":"19:49:49.685","dependents":[362],"id":90,"thread":"build-9"},{"duration":6,"stepId":"io.quarkus.resteasy.reactive.server.deployment.ResteasyReactiveProcessor#recordableConstructor","started":"19:49:49.580","dependents":[376],"id":39,"thread":"build-10"},{"duration":6,"stepId":"io.quarkus.netty.deployment.NettyProcessor#cleanup","started":"19:49:49.745","dependents":[152,289],"id":141,"thread":"build-18"},{"duration":6,"stepId":"io.quarkus.resteasy.reactive.jackson.deployment.processor.ResteasyReactiveJacksonProcessor#beans","started":"19:49:49.491","dependents":[291,301],"id":19,"thread":"build-6"},{"duration":6,"stepId":"io.quarkus.resteasy.reactive.server.deployment.ResteasyReactiveProcessor#securityExceptionMappers","started":"19:49:49.491","dependents":[273],"id":22,"thread":"build-1"},{"duration":6,"stepId":"io.quarkus.jackson.deployment.JacksonProcessor#unremovable","started":"19:49:50.204","dependents":[328],"id":251,"thread":"build-7"},{"duration":6,"stepId":"io.quarkus.resteasy.reactive.common.deployment.ResteasyReactiveCommonProcessor#handleApplication","started":"19:49:50.207","dependents":[269,346,356,259,375,355,342,267,273,265,272,264,263],"id":258,"thread":"build-22"},{"duration":6,"stepId":"io.quarkus.resteasy.reactive.server.deployment.devconsole.ResteasyReactiveDevConsoleProcessor#collectStaticResourcesInfo","started":"19:49:50.198","dependents":[362],"id":230,"thread":"build-2"},{"duration":6,"stepId":"io.quarkus.vertx.http.deployment.devmode.tests.TestsProcessor#printfailures","started":"19:49:49.743","dependents":[370,309],"id":139,"thread":"build-21"},{"duration":6,"stepId":"io.quarkus.resteasy.reactive.server.deployment.ResteasyReactiveDevModeProcessor#addStaticResourcesExceptionMapper","started":"19:49:50.195","dependents":[376],"id":223,"thread":"build-14"},{"duration":5,"stepId":"io.quarkus.vertx.http.deployment.devmode.console.DevConsoleProcessor#builder","started":"19:49:49.728","dependents":[370,309],"id":108,"thread":"build-1"},{"duration":5,"stepId":"io.quarkus.vertx.core.deployment.VertxCoreProcessor#build_9fb3ce360263cc99d07c9172ec2feeaa85afcc1a","started":"19:49:49.826","dependents":[361,203,374,371,324,372,323,343,363,373,325,214,376,320],"id":199,"thread":"build-11"},{"duration":5,"stepId":"io.quarkus.resteasy.reactive.common.deployment.ResteasyReactiveCommonProcessor#scanResources","started":"19:49:50.207","dependents":[260,346,356,301,257,261,342,268,271,349],"id":256,"thread":"build-4"},{"duration":5,"stepId":"io.quarkus.vertx.http.deployment.devmode.tests.TestsProcessor#handleTestResult","started":"19:49:49.747","dependents":[370,309],"id":146,"thread":"build-9"},{"duration":5,"stepId":"io.quarkus.vertx.http.deployment.StaticResourcesProcessor#collectStaticResources","started":"19:49:50.195","dependents":[343],"id":222,"thread":"build-16"},{"duration":5,"stepId":"io.quarkus.hibernate.orm.panache.deployment.PanacheHibernateResourceProcessor#build","started":"19:49:52.228","dependents":[368,376],"id":367,"thread":"build-26"},{"duration":5,"stepId":"io.quarkus.deployment.recording.substitutions.AdditionalSubstitutionsBuildStep#additionalSubstitutions","started":"19:49:49.746","dependents":[376],"id":142,"thread":"build-12"},{"duration":5,"stepId":"io.quarkus.arc.deployment.ArcProcessor#unremovableAsyncObserverExceptionHandlers","started":"19:49:49.748","dependents":[328],"id":147,"thread":"build-22"},{"duration":5,"stepId":"io.quarkus.arc.deployment.CommandLineArgumentsProcessor#commandLineArgs","started":"19:49:49.747","dependents":[291,325,324,301,323],"id":143,"thread":"build-16"},{"duration":5,"stepId":"io.quarkus.hibernate.orm.deployment.HibernateOrmProcessor#includeArchivesHostingEntityPackagesInIndex","started":"19:49:49.686","dependents":[220],"id":92,"thread":"build-11"},{"duration":5,"stepId":"io.quarkus.deployment.dev.testing.TestTracingProcessor#startTesting","started":"19:49:49.915","dependents":[373,371,289,372],"id":217,"thread":"build-18"},{"duration":5,"stepId":"io.quarkus.vertx.http.deployment.VertxHttpProcessor#logging","started":"19:49:49.760","dependents":[180],"id":168,"thread":"build-24"},{"duration":5,"stepId":"io.quarkus.vertx.http.deployment.devmode.tests.TestsProcessor#handleTestStatus","started":"19:49:49.746","dependents":[370,309],"id":145,"thread":"build-11"},{"duration":5,"stepId":"io.quarkus.resteasy.reactive.server.deployment.ResteasyReactiveDevModeProcessor#setupExceptionMapper","started":"19:49:49.632","dependents":[376,271],"id":75,"thread":"build-9"},{"duration":4,"stepId":"io.quarkus.deployment.JniProcessor#setupJni","started":"19:49:49.685","dependents":[322],"id":91,"thread":"build-16"},{"duration":4,"stepId":"io.quarkus.arc.deployment.SyntheticBeansProcessor#initStatic","started":"19:49:50.643","dependents":[326,376],"id":323,"thread":"build-28"},{"duration":4,"stepId":"io.quarkus.deployment.console.ConsoleProcessor#setupExceptionHandler","started":"19:49:49.917","dependents":[221],"id":219,"thread":"build-20"},{"duration":4,"stepId":"io.quarkus.deployment.steps.ConfigGenerationBuildStep#watchConfigFiles","started":"19:49:49.488","dependents":[287],"id":15,"thread":"build-3"},{"duration":4,"stepId":"io.quarkus.resteasy.reactive.server.deployment.ResteasyReactiveScanningProcessor#scanForContextResolvers","started":"19:49:50.214","dependents":[291,356,375,301],"id":269,"thread":"build-9"},{"duration":4,"stepId":"io.quarkus.vertx.http.deployment.devmode.tests.TestsProcessor#forceRestart","started":"19:49:49.476","dependents":[370,309],"id":1,"thread":"build-1"},{"duration":4,"stepId":"io.quarkus.resteasy.reactive.server.deployment.ResteasyReactiveScanningProcessor#scanForExceptionMappers","started":"19:49:50.255","dependents":[291,356,375,301],"id":273,"thread":"build-8"},{"duration":4,"stepId":"io.quarkus.hibernate.orm.panache.deployment.PanacheHibernateResourceProcessor#ensureBeanLookupAvailable","started":"19:49:49.501","dependents":[328],"id":27,"thread":"build-7"},{"duration":4,"stepId":"io.quarkus.agroal.deployment.AgroalMetricsProcessor#registerMetrics","started":"19:49:49.859","dependents":[376],"id":206,"thread":"build-4"},{"duration":4,"stepId":"io.quarkus.vertx.deployment.VertxProcessor#build","started":"19:49:50.629","dependents":[373,371,375,321,372,376],"id":320,"thread":"build-14"},{"duration":3,"stepId":"io.quarkus.hibernate.orm.deployment.HibernateOrmProcessor#handleMoveSql","started":"19:49:49.642","dependents":[372],"id":81,"thread":"build-12"},{"duration":3,"stepId":"io.quarkus.arc.deployment.devconsole.ArcDevConsoleProcessor#monitor","started":"19:49:49.765","dependents":[291,301,372],"id":169,"thread":"build-19"},{"duration":3,"stepId":"io.quarkus.arc.deployment.BuildTimeEnabledProcessor#buildExclusions","started":"19:49:50.207","dependents":[253],"id":252,"thread":"build-9"},{"duration":3,"stepId":"io.quarkus.deployment.CollectionClassProcessor#setupCollectionClasses","started":"19:49:49.495","dependents":[375],"id":21,"thread":"build-2"},{"duration":3,"stepId":"io.quarkus.vertx.http.deployment.devmode.ArcDevProcessor#registerRoutes","started":"19:49:50.808","dependents":[340,361,357,370,359,376,358],"id":336,"thread":"build-8"},{"duration":3,"stepId":"io.quarkus.deployment.steps.BootstrapConfigSetupBuildStep#setupBootstrapConfig","started":"19:49:49.760","dependents":[376,162],"id":159,"thread":"build-27"},{"duration":3,"stepId":"io.quarkus.arc.deployment.ConfigBuildStep#registerConfigRootsAsBeans","started":"19:49:49.632","dependents":[325,324,323],"id":73,"thread":"build-5"},{"duration":3,"stepId":"io.quarkus.narayana.jta.deployment.NarayanaJtaProcessor#transactionContext","started":"19:49:50.391","dependents":[310],"id":304,"thread":"build-11"},{"duration":3,"stepId":"io.quarkus.resteasy.reactive.jackson.deployment.processor.ResteasyReactiveJacksonProcessor#additionalProviders","started":"19:49:51.627","dependents":[355,352,353],"id":351,"thread":"build-28"},{"duration":3,"stepId":"io.quarkus.resteasy.reactive.server.deployment.ResteasyReactiveProcessor#responseHeaderSupport","started":"19:49:49.618","dependents":[346],"id":55,"thread":"build-1"},{"duration":3,"stepId":"io.quarkus.resteasy.reactive.common.deployment.ResteasyReactiveCommonProcessor#buildResourceInterceptors","started":"19:49:50.256","dependents":[291,356,301],"id":272,"thread":"build-9"},{"duration":3,"stepId":"io.quarkus.smallrye.context.deployment.SmallRyeContextPropagationProcessor#build","started":"19:49:49.829","dependents":[325,324,323,376],"id":200,"thread":"build-28"},{"duration":3,"stepId":"io.quarkus.datasource.deployment.devservices.DevServicesDatasourceProcessor#launchDatabases","started":"19:49:50.352","dependents":[302,299],"id":290,"thread":"build-11"},{"duration":3,"stepId":"io.quarkus.jackson.deployment.JacksonProcessor#generateCustomizer","started":"19:49:50.209","dependents":[291],"id":255,"thread":"build-20"},{"duration":3,"stepId":"io.quarkus.mutiny.deployment.MutinyProcessor#runtimeInit","started":"19:49:49.825","dependents":[376],"id":198,"thread":"build-28"},{"duration":3,"stepId":"io.quarkus.arc.deployment.ArcProcessor#feature","started":"19:49:49.535","dependents":[376],"id":31,"thread":"build-10"},{"duration":3,"stepId":"io.quarkus.vertx.http.deployment.VertxHttpProcessor#filterMultipleVertxInstancesWarning","started":"19:49:49.623","dependents":[152,289],"id":59,"thread":"build-1"},{"duration":3,"stepId":"io.quarkus.arc.deployment.staticmethods.InterceptedStaticMethodsProcessor#collectInterceptedStaticMethods","started":"19:49:50.627","dependents":[319,328,345],"id":318,"thread":"build-22"},{"duration":3,"stepId":"io.quarkus.deployment.steps.BlockingOperationControlBuildStep#blockingOP","started":"19:49:49.810","dependents":[376],"id":192,"thread":"build-28"},{"duration":3,"stepId":"io.quarkus.vertx.http.deployment.StaticResourcesProcessor#runtimeInit","started":"19:49:51.524","dependents":[376,363],"id":343,"thread":"build-14"},{"duration":3,"stepId":"io.quarkus.resteasy.reactive.server.deployment.ResteasyReactiveProcessor#registerCustomExceptionMappers","started":"19:49:49.494","dependents":[271],"id":23,"thread":"build-4"},{"duration":2,"stepId":"io.quarkus.panache.common.deployment.PanacheHibernateCommonResourceProcessor#findEntityClasses","started":"19:49:50.288","dependents":[366],"id":277,"thread":"build-28"},{"duration":2,"stepId":"io.quarkus.vertx.deployment.VertxProcessor#registerVerticleClasses","started":"19:49:50.205","dependents":[375],"id":239,"thread":"build-17"},{"duration":2,"stepId":"io.quarkus.devservices.postgresql.deployment.PostgresqlDevServicesProcessor#psqlCommand","started":"19:49:50.393","dependents":[350],"id":305,"thread":"build-5"},{"duration":2,"stepId":"io.quarkus.resteasy.reactive.jackson.deployment.processor.ResteasyReactiveJacksonProcessor#exceptionMappers","started":"19:49:49.584","dependents":[273],"id":40,"thread":"build-7"},{"duration":2,"stepId":"io.quarkus.jackson.deployment.JacksonProcessor#supportMixins","started":"19:49:50.205","dependents":[325,375,324,323,376],"id":238,"thread":"build-9"},{"duration":2,"stepId":"io.quarkus.arc.deployment.ConfigBuildStep#registerConfigClasses","started":"19:49:50.812","dependents":[376],"id":337,"thread":"build-28"},{"duration":2,"stepId":"io.quarkus.hibernate.orm.deployment.HibernateOrmCdiProcessor#convertJpaResourceAnnotationsToQualifier","started":"19:49:50.310","dependents":[301],"id":280,"thread":"build-9"},{"duration":2,"stepId":"io.quarkus.hibernate.orm.deployment.HibernateOrmProcessor#build_8ff77f88044a427fb6a033e68fe757357dc13b1d","started":"19:49:50.310","dependents":[367,325,324,323,376],"id":284,"thread":"build-14"},{"duration":2,"stepId":"io.quarkus.hibernate.orm.deployment.HibernateOrmProcessor#contributeQuarkusConfigToJpaModel","started":"19:49:49.696","dependents":[274],"id":97,"thread":"build-17"},{"duration":2,"stepId":"io.quarkus.deployment.steps.NativeImageConfigBuildStep#build","started":"19:49:50.642","dependents":[376],"id":322,"thread":"build-2"},{"duration":2,"stepId":"io.quarkus.arc.deployment.ArcProcessor#launchMode","started":"19:49:49.491","dependents":[291,301],"id":16,"thread":"build-4"},{"duration":2,"stepId":"io.quarkus.deployment.dev.io.NioThreadPoolDevModeProcessor#setupTCCL","started":"19:49:49.737","dependents":[376],"id":113,"thread":"build-15"},{"duration":2,"stepId":"io.quarkus.deployment.logging.LoggingResourceProcessor#setupStackTraceFormatter","started":"19:49:50.195","dependents":[289],"id":221,"thread":"build-5"},{"duration":2,"stepId":"io.quarkus.hibernate.orm.deployment.HibernateOrmProcessor#devServicesAutoGenerateByDefault","started":"19:49:50.309","dependents":[299],"id":281,"thread":"build-1"},{"duration":2,"stepId":"io.quarkus.credentials.CredentialsProcessor#registerAdditionalBeans","started":"19:49:49.748","dependents":[291,301],"id":140,"thread":"build-27"},{"duration":2,"stepId":"io.quarkus.hibernate.orm.deployment.devconsole.HibernateDevConsoleProcessor#collectDeploymentUnits","started":"19:49:49.648","dependents":[372],"id":89,"thread":"build-9"},{"duration":2,"stepId":"io.quarkus.deployment.steps.ConfigBuildSteps#generateConfigSources","started":"19:49:49.623","dependents":[],"id":58,"thread":"build-3"},{"duration":2,"stepId":"io.quarkus.vertx.core.deployment.VertxCoreProcessor#registerVerticleClasses","started":"19:49:50.204","dependents":[375],"id":240,"thread":"build-4"},{"duration":2,"stepId":"io.quarkus.arc.deployment.AutoAddScopeProcessor#annotationTransformer","started":"19:49:50.359","dependents":[328,301],"id":297,"thread":"build-11"},{"duration":2,"stepId":"io.quarkus.netty.deployment.NettyProcessor#eagerlyInitClass","started":"19:49:49.761","dependents":[376],"id":161,"thread":"build-4"},{"duration":2,"stepId":"io.quarkus.hibernate.orm.panache.deployment.PanacheHibernateResourceProcessor#validate","started":"19:49:50.808","dependents":[340],"id":334,"thread":"build-28"},{"duration":2,"stepId":"io.quarkus.netty.deployment.NettyProcessor#registerEventLoopBeans","started":"19:49:49.836","dependents":[325,324,323,376],"id":203,"thread":"build-9"},{"duration":2,"stepId":"io.quarkus.vertx.http.deployment.devmode.console.DevConsoleProcessor#buildTimeTemplates","started":"19:49:51.674","dependents":[373,371,372],"id":362,"thread":"build-14"},{"duration":2,"stepId":"io.quarkus.vertx.http.deployment.VertxHttpProcessor#initializeRouter","started":"19:49:51.674","dependents":[376,363],"id":361,"thread":"build-16"},{"duration":1,"stepId":"io.quarkus.deployment.steps.ConfigGenerationBuildStep#suppressNonRuntimeConfigChanged","started":"19:49:49.495","dependents":[298],"id":18,"thread":"build-5"},{"duration":1,"stepId":"io.quarkus.resteasy.reactive.server.deployment.ResteasyReactiveDevModeProcessor#openCommand","started":"19:49:51.624","dependents":[350],"id":348,"thread":"build-28"},{"duration":1,"stepId":"io.quarkus.vertx.http.deployment.devmode.tests.TestsProcessor#toggleTestRunner","started":"19:49:49.485","dependents":[370,309],"id":8,"thread":"build-3"},{"duration":1,"stepId":"io.quarkus.resteasy.reactive.jackson.deployment.processor.ResteasyReactiveJacksonProcessor#handleJsonAnnotations","started":"19:49:51.625","dependents":[351,375,376],"id":349,"thread":"build-8"},{"duration":1,"stepId":"io.quarkus.hibernate.orm.panache.common.deployment.PanacheJpaCommonResourceProcessor#lookupNamedQueries_5a86a91ed8ef1aa483288c8239df231983eeb766","started":"19:49:50.288","dependents":[278],"id":276,"thread":"build-16"},{"duration":1,"stepId":"io.quarkus.arc.deployment.ReflectiveBeanClassesProcessor#implicitReflectiveBeanClasses","started":"19:49:50.626","dependents":[340],"id":314,"thread":"build-1"},{"duration":1,"stepId":"io.quarkus.resteasy.reactive.server.deployment.ResteasyReactiveProcessor#setMinimalNettyMaxOrderSize","started":"19:49:49.494","dependents":[71,68],"id":17,"thread":"build-7"},{"duration":1,"stepId":"io.quarkus.smallrye.context.deployment.SmallRyeContextPropagationProcessor#createSynthBeansForConfiguredInjectionPoints","started":"19:49:50.626","dependents":[325,324,323,376],"id":315,"thread":"build-14"},{"duration":1,"stepId":"io.quarkus.hibernate.orm.panache.deployment.PanacheHibernateResourceProcessor#produceModel","started":"19:49:49.740","dependents":[237,365],"id":118,"thread":"build-4"},{"duration":1,"stepId":"io.quarkus.smallrye.context.deployment.SmallRyeContextPropagationProcessor#transformInjectionPoint","started":"19:49:49.483","dependents":[301],"id":3,"thread":"build-2"},{"duration":1,"stepId":"io.quarkus.vertx.http.deployment.VertxHttpProcessor#additionalBeans","started":"19:49:49.488","dependents":[291,301],"id":10,"thread":"build-1"},{"duration":1,"stepId":"io.quarkus.deployment.steps.ShutdownListenerBuildStep#setupShutdown","started":"19:49:51.685","dependents":[376],"id":364,"thread":"build-26"},{"duration":1,"stepId":"io.quarkus.vertx.deployment.EventBusCodecProcessor#registerCodecs","started":"19:49:50.358","dependents":[375,320],"id":296,"thread":"build-5"},{"duration":1,"stepId":"io.quarkus.deployment.dev.testing.TestTracingProcessor#handle","started":"19:49:49.485","dependents":[152,289],"id":7,"thread":"build-1"},{"duration":1,"stepId":"io.quarkus.resteasy.reactive.common.deployment.ResteasyReactiveCommonProcessor#setupEndpoints","started":"19:49:51.524","dependents":[375,355,352,353],"id":342,"thread":"build-28"},{"duration":1,"stepId":"io.quarkus.resteasy.reactive.server.deployment.ResteasyReactiveProcessor#applyRuntimeConfig","started":"19:49:51.674","dependents":[376],"id":360,"thread":"build-8"},{"duration":1,"stepId":"io.quarkus.deployment.pkg.steps.JarResultBuildStep#outputTarget","started":"19:49:49.637","dependents":[77],"id":76,"thread":"build-12"},{"duration":1,"stepId":"io.quarkus.resteasy.reactive.server.deployment.ResteasyReactiveScanningProcessor#asyncSupport","started":"19:49:49.488","dependents":[346],"id":12,"thread":"build-5"},{"duration":1,"stepId":"io.quarkus.arc.deployment.ArcProcessor#transformListAllInjectionPoints","started":"19:49:49.526","dependents":[301],"id":29,"thread":"build-7"},{"duration":1,"stepId":"io.quarkus.resteasy.reactive.server.deployment.ResteasyReactiveProcessor#responseStatusSupport","started":"19:49:49.739","dependents":[346],"id":119,"thread":"build-6"},{"duration":1,"stepId":"io.quarkus.hibernate.orm.panache.common.deployment.PanacheJpaCommonResourceProcessor#buildNamedQueryMap","started":"19:49:50.289","dependents":[376],"id":278,"thread":"build-9"},{"duration":1,"stepId":"io.quarkus.vertx.http.deployment.devmode.console.ConfigEditorProcessor#handleRequests","started":"19:49:50.381","dependents":[370,309],"id":300,"thread":"build-11"},{"duration":1,"stepId":"io.quarkus.deployment.logging.LoggingResourceProcessor#setUpDefaultLogCleanupFilters","started":"19:49:49.755","dependents":[307],"id":152,"thread":"build-27"},{"duration":1,"stepId":"io.quarkus.hibernate.orm.deployment.HibernateOrmCdiProcessor#validatePersistenceUnitExtensions","started":"19:49:50.808","dependents":[340],"id":333,"thread":"build-16"},{"duration":1,"stepId":"io.quarkus.panache.common.deployment.PanacheHibernateCommonResourceProcessor#replaceFieldAccesses","started":"19:49:52.228","dependents":[368],"id":366,"thread":"build-8"},{"duration":1,"stepId":"io.quarkus.hibernate.orm.deployment.HibernateOrmProcessor#jpaEntitiesIndexer","started":"19:49:50.205","dependents":[274,369],"id":237,"thread":"build-18"},{"duration":0,"stepId":"io.quarkus.jdbc.postgresql.deployment.JDBCPostgreSQLProcessor#feature","started":"19:49:49.774","dependents":[376],"id":177,"thread":"build-12"},{"duration":0,"stepId":"io.quarkus.resteasy.reactive.server.deployment.ResteasyReactiveProcessor#integrateEagerSecurity","started":"19:49:50.209","dependents":[346],"id":248,"thread":"build-1"},{"duration":0,"stepId":"io.quarkus.resteasy.reactive.common.deployment.ResteasyReactiveCommonProcessor#deprioritizeLegacyProviders","started":"19:49:49.737","dependents":[355],"id":110,"thread":"build-6"},{"duration":0,"stepId":"io.quarkus.arc.deployment.BuildTimeEnabledProcessor#unlessBuildProperty","started":"19:49:50.204","dependents":[252,245,258],"id":232,"thread":"build-9"},{"duration":0,"stepId":"io.quarkus.deployment.steps.ReflectiveHierarchyStep#ignoreJavaClassWarnings","started":"19:49:49.570","dependents":[354],"id":37,"thread":"build-10"},{"duration":0,"stepId":"io.quarkus.deployment.steps.ConfigGenerationBuildStep#staticInitSources","started":"19:49:49.485","dependents":[339],"id":6,"thread":"build-4"},{"duration":0,"stepId":"io.quarkus.deployment.steps.NativeImageResourcesStep#registerPackageResources","started":"19:49:49.566","dependents":[308],"id":35,"thread":"build-8"},{"duration":0,"stepId":"io.quarkus.resteasy.reactive.server.deployment.ResteasyReactiveCDIProcessor#additionalBeans","started":"19:49:50.215","dependents":[291,375,301],"id":266,"thread":"build-11"},{"duration":0,"stepId":"io.quarkus.resteasy.reactive.server.deployment.ResteasyReactiveVertxWebSocketIntegrationProcessor#scanner","started":"19:49:49.628","dependents":[346],"id":61,"thread":"build-7"},{"duration":0,"stepId":"io.quarkus.netty.deployment.NettyProcessor#build","started":"19:49:49.633","dependents":[322,375],"id":71,"thread":"build-2"},{"duration":0,"stepId":"io.quarkus.deployment.console.ConsoleProcessor#installCliCommands","started":"19:49:51.626","dependents":[373,371,372],"id":350,"thread":"build-16"},{"duration":0,"stepId":"io.quarkus.vertx.core.deployment.VertxCoreProcessor#cleanupVertxWarnings","started":"19:49:49.622","dependents":[152,289],"id":56,"thread":"build-1"},{"duration":0,"stepId":"io.quarkus.arc.deployment.UnremovableAnnotationsProcessor#unremovableBeans","started":"19:49:49.618","dependents":[328],"id":54,"thread":"build-3"},{"duration":0,"stepId":"io.quarkus.arc.deployment.configproperties.ConfigPropertiesBuildStep#produceConfigPropertiesMetadata","started":"19:49:50.211","dependents":[254],"id":253,"thread":"build-7"},{"duration":0,"stepId":"io.quarkus.arc.deployment.ConfigBuildStep#additionalBeans","started":"19:49:49.773","dependents":[291,301],"id":176,"thread":"build-21"},{"duration":0,"stepId":"io.quarkus.hibernate.orm.deployment.HibernateOrmProcessor#startPersistenceUnits","started":"19:49:51.533","dependents":[373,371,372,376],"id":344,"thread":"build-14"},{"duration":0,"stepId":"io.quarkus.deployment.steps.ConfigGenerationBuildStep#setupConfigOverride","started":"19:49:49.774","dependents":[],"id":178,"thread":"build-6"},{"duration":0,"stepId":"io.quarkus.jackson.deployment.JacksonProcessor#register","started":"19:49:50.204","dependents":[291,354,375,301],"id":231,"thread":"build-18"},{"duration":0,"stepId":"io.quarkus.resteasy.reactive.server.deployment.ResteasyReactiveScanningProcessor#scanForParamConverters_dcdfdd2a310a09abe5ee3f0ed2b2bc49f36f3d07","started":"19:49:50.215","dependents":[291,346,356,375,301],"id":262,"thread":"build-22"},{"duration":0,"stepId":"io.quarkus.deployment.steps.ProfileBuildStep#defaultProfile","started":"19:49:49.739","dependents":[307],"id":115,"thread":"build-15"},{"duration":0,"stepId":"io.quarkus.hibernate.orm.deployment.ResteasyReactiveServerIntegrationProcessor#unwrappedExceptions","started":"19:49:49.501","dependents":[273],"id":25,"thread":"build-2"},{"duration":0,"stepId":"io.quarkus.deployment.steps.NativeImageFeatureStep#generateNativeResourcesList","started":"19:49:50.407","dependents":[],"id":308,"thread":"build-14"},{"duration":0,"stepId":"io.quarkus.resteasy.reactive.server.deployment.ResteasyReactiveProcessor#handleClassLevelExceptionMappers","started":"19:49:50.213","dependents":[346,375],"id":257,"thread":"build-9"},{"duration":0,"stepId":"io.quarkus.deployment.steps.CurateOutcomeBuildStep#removeResources","started":"19:49:49.698","dependents":[368],"id":96,"thread":"build-18"},{"duration":0,"stepId":"io.quarkus.arc.deployment.ConfigBuildStep#validateConfigMappingsInjectionPoints","started":"19:49:50.811","dependents":[337,339],"id":335,"thread":"build-26"},{"duration":0,"stepId":"io.quarkus.hibernate.orm.deployment.HibernateOrmProcessor#defineTypeOfImpliedPU","started":"19:49:49.890","dependents":[280,279,286],"id":210,"thread":"build-9"},{"duration":0,"stepId":"io.quarkus.arc.deployment.ConfigBuildStep#registerConfigMappingConverters","started":"19:49:50.203","dependents":[375],"id":229,"thread":"build-14"},{"duration":0,"stepId":"io.quarkus.arc.deployment.ConfigBuildStep#vetoMPConfigProperties","started":"19:49:49.483","dependents":[301],"id":4,"thread":"build-1"},{"duration":0,"stepId":"io.quarkus.deployment.steps.MainClassBuildStep#applicationReflection","started":"19:49:49.737","dependents":[375],"id":109,"thread":"build-7"},{"duration":0,"stepId":"io.quarkus.arc.deployment.TestsAsBeansProcessor#testAnnotations","started":"19:49:49.739","dependents":[291,169,301],"id":116,"thread":"build-7"},{"duration":0,"stepId":"io.quarkus.reactive.pg.client.deployment.ReactivePgClientProcessor#devDbHandler","started":"19:49:49.760","dependents":[290],"id":155,"thread":"build-28"},{"duration":0,"stepId":"io.quarkus.smallrye.context.deployment.SmallRyeContextPropagationProcessor#registerBean","started":"19:49:49.499","dependents":[291,301],"id":24,"thread":"build-9"},{"duration":0,"stepId":"io.quarkus.vertx.http.deployment.devmode.tests.TestsProcessor#results","started":"19:49:49.743","dependents":[362],"id":122,"thread":"build-21"},{"duration":0,"stepId":"io.quarkus.reactive.pg.client.deployment.ReactivePgClientProcessor#registerServiceBinding","started":"19:49:49.768","dependents":[205,290,321],"id":173,"thread":"build-19"},{"duration":0,"stepId":"io.quarkus.arc.deployment.HotDeploymentConfigBuildStep#startup","started":"19:49:49.485","dependents":[9],"id":5,"thread":"build-2"},{"duration":0,"stepId":"io.quarkus.deployment.ide.IdeProcessor#effectiveIde","started":"19:49:49.727","dependents":[219,221,370,108],"id":107,"thread":"build-6"},{"duration":0,"stepId":"io.quarkus.deployment.steps.AdditionalClassLoaderResourcesBuildStep#appendAdditionalClassloaderResources","started":"19:49:49.491","dependents":[224],"id":13,"thread":"build-2"},{"duration":0,"stepId":"io.quarkus.resteasy.reactive.common.deployment.ResteasyReactiveCommonProcessor#resourceIndex","started":"19:49:50.207","dependents":[291,256,347],"id":243,"thread":"build-18"},{"duration":0,"stepId":"io.quarkus.hibernate.orm.deployment.HibernateOrmProcessor#candidatesForFieldAccess","started":"19:49:50.288","dependents":[277],"id":275,"thread":"build-9"},{"duration":0,"stepId":"io.quarkus.arc.deployment.staticmethods.InterceptedStaticMethodsProcessor#callInitializer","started":"19:49:51.534","dependents":[376],"id":345,"thread":"build-14"},{"duration":0,"stepId":"io.quarkus.vertx.deployment.VertxProcessor#collectEventConsumers","started":"19:49:50.628","dependents":[326,320],"id":316,"thread":"build-2"},{"duration":0,"stepId":"io.quarkus.resteasy.reactive.server.deployment.ResteasyReactiveCDIProcessor#beanDefiningAnnotations","started":"19:49:49.764","dependents":[291,169,301],"id":163,"thread":"build-27"},{"duration":0,"stepId":"io.quarkus.netty.deployment.NettyProcessor#limitArenaSize","started":"19:49:49.631","dependents":[376],"id":68,"thread":"build-5"},{"duration":0,"stepId":"io.quarkus.vertx.deployment.VertxProcessor#unremovableBeans","started":"19:49:49.740","dependents":[328],"id":117,"thread":"build-21"},{"duration":0,"stepId":"io.quarkus.arc.deployment.ArcProcessor#validateAsyncObserverExceptionHandlers","started":"19:49:50.808","dependents":[340],"id":332,"thread":"build-5"},{"duration":0,"stepId":"io.quarkus.arc.deployment.configproperties.ConfigPropertiesBuildStep#setup","started":"19:49:50.212","dependents":[291,307,375,341],"id":254,"thread":"build-9"},{"duration":0,"stepId":"io.quarkus.resteasy.reactive.server.deployment.devconsole.ResteasyReactiveDevConsoleProcessor#exceptionMappers","started":"19:49:49.649","dependents":[372],"id":85,"thread":"build-16"},{"duration":0,"stepId":"io.quarkus.deployment.index.ApplicationArchiveBuildStep#addConfiguredIndexedDependencies","started":"19:49:49.635","dependents":[220],"id":74,"thread":"build-5"},{"duration":0,"stepId":"io.quarkus.arc.deployment.TestsAsBeansProcessor#testClassBeans","started":"19:49:49.746","dependents":[291,301],"id":129,"thread":"build-12"},{"duration":0,"stepId":"io.quarkus.arc.deployment.ArcProcessor#quarkusApplication","started":"19:49:50.208","dependents":[291,301],"id":249,"thread":"build-16"},{"duration":0,"stepId":"io.quarkus.vertx.http.deployment.VertxHttpProcessor#httpRoot","started":"19:49:49.631","dependents":[101,75,359,363,348],"id":70,"thread":"build-2"},{"duration":0,"stepId":"io.quarkus.deployment.ide.IdeProcessor#detectIdeFiles","started":"19:49:49.618","dependents":[107],"id":53,"thread":"build-3"},{"duration":0,"stepId":"io.quarkus.arc.deployment.ArcProcessor#marker","started":"19:49:49.748","dependents":[220],"id":135,"thread":"build-24"},{"duration":0,"stepId":"io.quarkus.resteasy.reactive.server.deployment.ResteasyReactiveProcessor#unremovableBeans","started":"19:49:50.214","dependents":[328],"id":260,"thread":"build-20"},{"duration":0,"stepId":"io.quarkus.deployment.ExtensionLoader#config","started":"19:49:49.630","dependents":[81,364,104,191,120,371,217,186,68,70,69,73,204,71,360,301,214,321,72,74,218,80,84,291,215,76,199,189,79,298,193,78,226,195,253,187,87,90,91,340,281,279,361,92,250,295,335,339,207,336,248,363,190,373,258,169,94,194,289,206,201,376,213,317,185,216,329,346,356,374,95,97,343,235,284,96,285,205,290,98,99,368,107,197,293,100,220],"id":67,"thread":"build-8"},{"duration":0,"stepId":"io.quarkus.deployment.logging.LoggingResourceProcessor#setProperty","started":"19:49:49.501","dependents":[376],"id":26,"thread":"build-5"},{"duration":0,"stepId":"io.quarkus.arc.deployment.ArcProcessor#quarkusMain","started":"19:49:49.630","dependents":[291,169,301],"id":64,"thread":"build-8"},{"duration":0,"stepId":"io.quarkus.vertx.http.deployment.devmode.BuildMetricsDevConsoleProcessor#collectMetrics","started":"19:49:49.776","dependents":[362],"id":181,"thread":"build-6"},{"duration":0,"stepId":"io.quarkus.hibernate.orm.deployment.HibernateOrmProcessor#contributePersistenceXmlToJpaModel","started":"19:49:49.891","dependents":[274],"id":212,"thread":"build-14"},{"duration":0,"stepId":"io.quarkus.deployment.steps.RegisterForReflectionBuildStep#build","started":"19:49:50.204","dependents":[375],"id":233,"thread":"build-8"},{"duration":0,"stepId":"io.quarkus.arc.deployment.AutoInjectFieldProcessor#autoInjectQualifiers","started":"19:49:50.359","dependents":[295,297],"id":294,"thread":"build-16"},{"duration":0,"stepId":"io.quarkus.vertx.http.deployment.VertxHttpProcessor#hostDefault","started":"19:49:49.622","dependents":[58],"id":57,"thread":"build-1"},{"duration":0,"stepId":"io.quarkus.resteasy.reactive.server.deployment.devconsole.ResteasyReactiveDevConsoleProcessor#collectScores","started":"19:49:49.649","dependents":[372],"id":86,"thread":"build-11"},{"duration":0,"stepId":"io.quarkus.deployment.steps.BannerProcessor#watchBannerChanges","started":"19:49:49.699","dependents":[287],"id":98,"thread":"build-19"},{"duration":0,"stepId":"io.quarkus.arc.deployment.ArcProcessor#exposeCustomScopeNames","started":"19:49:49.764","dependents":[291,317,167,293,169,301,297],"id":166,"thread":"build-27"},{"duration":0,"stepId":"io.quarkus.deployment.logging.LoggingResourceProcessor#setUpDarkeningDefault","started":"19:49:49.488","dependents":[307],"id":11,"thread":"build-2"},{"duration":0,"stepId":"io.quarkus.resteasy.reactive.server.deployment.ResteasyReactiveScanningProcessor#scanForFeatures","started":"19:49:50.215","dependents":[356,266],"id":264,"thread":"build-5"},{"duration":0,"stepId":"io.quarkus.hibernate.orm.deployment.HibernateOrmProcessor#produceLoggingCategories","started":"19:49:49.634","dependents":[180],"id":72,"thread":"build-2"},{"duration":0,"stepId":"io.quarkus.hibernate.orm.deployment.HibernateOrmProcessor#multitenancy","started":"19:49:50.312","dependents":[325,328,324,323,376],"id":282,"thread":"build-28"},{"duration":0,"stepId":"io.quarkus.arc.deployment.BuildTimeEnabledProcessor#ifBuildProfile","started":"19:49:50.203","dependents":[252,245,258],"id":227,"thread":"build-16"},{"duration":0,"stepId":"io.quarkus.deployment.steps.DevModeBuildStep#watchChanges","started":"19:49:49.700","dependents":[287],"id":100,"thread":"build-21"},{"duration":0,"stepId":"io.quarkus.resteasy.reactive.server.deployment.ResteasyReactiveProcessor#addAllWriteableMarker","started":"19:49:51.630","dependents":[368],"id":352,"thread":"build-8"},{"duration":0,"stepId":"io.quarkus.arc.deployment.WrongAnnotationUsageProcessor#detect","started":"19:49:50.628","dependents":[340],"id":317,"thread":"build-5"},{"duration":0,"stepId":"io.quarkus.deployment.dev.ConfigureDisableInstrumentationBuildStep#configure","started":"19:49:49.487","dependents":[373,371,372],"id":9,"thread":"build-4"},{"duration":0,"stepId":"io.quarkus.deployment.logging.LoggingWithPanacheProcessor#process","started":"19:49:50.205","dependents":[368],"id":234,"thread":"build-8"},{"duration":0,"stepId":"io.quarkus.arc.deployment.ConfigBuildStep#registerCustomConfigBeanTypes","started":"19:49:50.627","dependents":[325,375,324,323],"id":312,"thread":"build-16"},{"duration":0,"stepId":"io.quarkus.arc.deployment.BuildTimeEnabledProcessor#conditionTransformer","started":"19:49:50.207","dependents":[301],"id":245,"thread":"build-11"},{"duration":0,"stepId":"io.quarkus.vertx.http.deployment.devmode.console.DevConsoleProcessor#config","started":"19:49:50.393","dependents":[362],"id":303,"thread":"build-5"},{"duration":0,"stepId":"io.quarkus.deployment.steps.CurateOutcomeBuildStep#curateOutcome","started":"19:49:49.642","dependents":[81,120,93,370,309,82,362,83,96,89,290,205,85,164,204,306,368,169,321,220,86],"id":78,"thread":"build-14"},{"duration":0,"stepId":"io.quarkus.deployment.dev.testing.TestTracingProcessor#sharedStateListener","started":"19:49:49.587","dependents":[217],"id":41,"thread":"build-7"},{"duration":0,"stepId":"io.quarkus.vertx.http.deployment.devmode.console.DevConsoleProcessor#runtimeTemplates","started":"19:49:53.421","dependents":[376],"id":372,"thread":"build-22"},{"duration":0,"stepId":"io.quarkus.arc.deployment.ConfigBuildStep#registerConfigMappingsBean","started":"19:49:50.628","dependents":[326],"id":313,"thread":"build-28"},{"duration":0,"stepId":"io.quarkus.deployment.steps.ConfigGenerationBuildStep#extensionMappings","started":"19:49:50.209","dependents":[311,329,335,375,313],"id":250,"thread":"build-2"},{"duration":0,"stepId":"io.quarkus.arc.deployment.ConfigBuildStep#validateConfigInjectionPoints","started":"19:49:50.808","dependents":[341],"id":331,"thread":"build-2"},{"duration":0,"stepId":"io.quarkus.vertx.http.deployment.devmode.tests.TestsProcessor#toggleInstrumentation","started":"19:49:49.611","dependents":[370,309],"id":51,"thread":"build-3"},{"duration":0,"stepId":"io.quarkus.vertx.core.deployment.VertxCoreProcessor#preventLoggerContention","started":"19:49:49.776","dependents":[180],"id":179,"thread":"build-12"},{"duration":0,"stepId":"io.quarkus.deployment.ForkJoinPoolProcessor#setProperty","started":"19:49:49.630","dependents":[376],"id":62,"thread":"build-5"},{"duration":0,"stepId":"io.quarkus.arc.deployment.StartupBuildSteps#registerStartupObservers","started":"19:49:50.682","dependents":[328],"id":327,"thread":"build-14"},{"duration":0,"stepId":"io.quarkus.resteasy.reactive.server.deployment.ResteasyReactiveProcessor#generateCustomProducer","started":"19:49:50.216","dependents":[291,301],"id":268,"thread":"build-2"},{"duration":0,"stepId":"io.quarkus.vertx.http.deployment.devmode.tests.TestsProcessor#toggleTestOutput","started":"19:49:49.608","dependents":[370,309],"id":48,"thread":"build-3"},{"duration":0,"stepId":"io.quarkus.resteasy.reactive.jackson.deployment.processor.ResteasyReactiveJacksonProcessor#customExceptionMappers","started":"19:49:49.483","dependents":[271],"id":2,"thread":"build-3"},{"duration":0,"stepId":"io.quarkus.vertx.http.deployment.devmode.tests.TestsProcessor#runAllTests","started":"19:49:49.491","dependents":[370,309],"id":14,"thread":"build-5"},{"duration":0,"stepId":"io.quarkus.arc.deployment.ObserverValidationProcessor#validateApplicationObserver","started":"19:49:50.808","dependents":[340],"id":330,"thread":"build-9"},{"duration":0,"stepId":"io.quarkus.deployment.steps.CapabilityAggregationStep#aggregateCapabilities","started":"19:49:49.764","dependents":[251,279,254,346,189,356,288,208,207,210,172,248,285,190,170,171,173,273,301,187,222,174],"id":164,"thread":"build-8"},{"duration":0,"stepId":"io.quarkus.arc.deployment.ConfigBuildStep#validateConfigPropertiesInjectionPoints","started":"19:49:50.808","dependents":[337],"id":329,"thread":"build-11"},{"duration":0,"stepId":"io.quarkus.hibernate.orm.deployment.HibernateOrmProcessor#enforceDisableRuntimeEnhancer","started":"19:49:49.618","dependents":[376],"id":52,"thread":"build-1"},{"duration":0,"stepId":"io.quarkus.agroal.deployment.AgroalProcessor#agroal","started":"19:49:49.746","dependents":[376],"id":132,"thread":"build-16"},{"duration":0,"stepId":"io.quarkus.vertx.deployment.VertxProcessor#featureAndCapability","started":"19:49:49.764","dependents":[164,376],"id":160,"thread":"build-27"},{"duration":0,"stepId":"io.quarkus.resteasy.reactive.server.deployment.devconsole.ResteasyReactiveDevConsoleProcessor#paramConverterProviders","started":"19:49:49.647","dependents":[372],"id":83,"thread":"build-2"},{"duration":0,"stepId":"io.quarkus.resteasy.reactive.server.deployment.ResteasyReactiveScanningProcessor#scanForParamConverters_59e3169e3a646b7fcf3083416f558434b73816c5","started":"19:49:50.214","dependents":[262],"id":259,"thread":"build-4"},{"duration":0,"stepId":"io.quarkus.resteasy.reactive.server.deployment.ResteasyReactiveProcessor#additionalAsyncTypeMethodScanners","started":"19:49:49.747","dependents":[346],"id":134,"thread":"build-22"},{"duration":0,"stepId":"io.quarkus.arc.deployment.HotDeploymentConfigBuildStep#configFile","started":"19:49:49.566","dependents":[287],"id":36,"thread":"build-8"},{"duration":0,"stepId":"io.quarkus.arc.deployment.BuildTimeEnabledProcessor#unlessBuildProfile","started":"19:49:50.207","dependents":[252,245,258],"id":242,"thread":"build-4"},{"duration":0,"stepId":"io.quarkus.deployment.pkg.steps.PackageTypeVerificationBuildStep#verify","started":"19:49:49.699","dependents":[373,371,372],"id":99,"thread":"build-20"},{"duration":0,"stepId":"io.quarkus.jdbc.postgresql.deployment.JDBCPostgreSQLProcessor#registerServiceBinding","started":"19:49:49.769","dependents":[205,290,321],"id":174,"thread":"build-27"},{"duration":0,"stepId":"io.quarkus.hibernate.orm.panache.deployment.PanacheHibernateResourceProcessor#marker","started":"19:49:49.609","dependents":[220],"id":49,"thread":"build-3"},{"duration":0,"stepId":"io.quarkus.arc.deployment.ConfigBuildStep#validateConfigValues","started":"19:49:51.525","dependents":[375,376],"id":341,"thread":"build-8"},{"duration":0,"stepId":"io.quarkus.jdbc.postgresql.deployment.JDBCPostgreSQLProcessor#configureAgroalConnection","started":"19:49:49.767","dependents":[291,301],"id":172,"thread":"build-28"},{"duration":0,"stepId":"io.quarkus.resteasy.reactive.server.deployment.ResteasyReactiveDevModeProcessor#addReactiveRoutesExceptionMapper","started":"19:49:49.739","dependents":[376],"id":114,"thread":"build-4"},{"duration":0,"stepId":"io.quarkus.deployment.logging.LoggingResourceProcessor#setupLogFilters","started":"19:49:49.743","dependents":[152,289],"id":125,"thread":"build-6"},{"duration":0,"stepId":"io.quarkus.arc.deployment.AutoProducerMethodsProcessor#annotationTransformer","started":"19:49:50.358","dependents":[301],"id":293,"thread":"build-14"},{"duration":0,"stepId":"io.quarkus.narayana.jta.deployment.NarayanaJtaProcessor#registerScope","started":"19:49:49.764","dependents":[166],"id":165,"thread":"build-28"},{"duration":0,"stepId":"io.quarkus.vertx.http.deployment.VertxHttpProcessor#notFoundRoutes","started":"19:49:51.674","dependents":[359,358],"id":357,"thread":"build-14"},{"duration":0,"stepId":"io.quarkus.deployment.steps.RuntimeConfigSetupBuildStep#setupRuntimeConfig","started":"19:49:49.763","dependents":[364,215,185,191,361,199,374,207,186,343,298,363,190,193,373,360,195,194,214,321,289,201,376,213],"id":162,"thread":"build-15"},{"duration":0,"stepId":"io.quarkus.deployment.SslProcessor#setupNativeSsl","started":"19:49:49.650","dependents":[88,208,322,207],"id":87,"thread":"build-11"},{"duration":0,"stepId":"io.quarkus.jdbc.postgresql.deployment.JDBCPostgreSQLProcessor#registerDriver","started":"19:49:49.650","dependents":[205],"id":88,"thread":"build-16"},{"duration":0,"stepId":"io.quarkus.deployment.steps.CapabilityAggregationStep#provideCapabilities","started":"19:49:49.647","dependents":[164],"id":82,"thread":"build-12"},{"duration":0,"stepId":"io.quarkus.resteasy.reactive.server.deployment.ResteasyReactiveScanningProcessor#scanForDynamicFeatures","started":"19:49:50.214","dependents":[356,266],"id":263,"thread":"build-11"},{"duration":0,"stepId":"io.quarkus.resteasy.reactive.server.deployment.ResteasyReactiveProcessor#additionalReflection","started":"19:49:51.630","dependents":[375],"id":353,"thread":"build-14"},{"duration":0,"stepId":"io.quarkus.resteasy.reactive.jackson.deployment.processor.ResteasyReactiveJacksonProcessor#handleFieldSecurity","started":"19:49:51.624","dependents":[349],"id":347,"thread":"build-14"},{"duration":0,"stepId":"io.quarkus.arc.deployment.BuildTimeEnabledProcessor#ifBuildProperty","started":"19:49:50.202","dependents":[252,245,258],"id":225,"thread":"build-9"},{"duration":0,"stepId":"io.quarkus.deployment.recording.AnnotationProxyBuildStep#build","started":"19:49:49.742","dependents":[320],"id":121,"thread":"build-6"},{"duration":0,"stepId":"io.quarkus.hibernate.orm.deployment.HibernateOrmProcessor#enrollBeanValidationTypeSafeActivatorForReflection","started":"19:49:49.768","dependents":[375],"id":170,"thread":"build-27"},{"duration":0,"stepId":"io.quarkus.arc.deployment.LookupConditionsProcessor#suppressConditionsGenerators","started":"19:49:50.358","dependents":[301],"id":292,"thread":"build-11"},{"duration":0,"stepId":"io.quarkus.jackson.deployment.JacksonProcessor#autoRegisterModules","started":"19:49:50.208","dependents":[255],"id":246,"thread":"build-5"},{"duration":0,"stepId":"io.quarkus.hibernate.orm.panache.deployment.PanacheHibernateResourceProcessor#collectEntityClasses","started":"19:49:50.208","dependents":[367],"id":247,"thread":"build-14"},{"duration":0,"stepId":"io.quarkus.deployment.pkg.steps.FileSystemResourcesBuildStep#notNormalMode","started":"19:49:49.639","dependents":[],"id":77,"thread":"build-13"},{"duration":0,"stepId":"io.quarkus.arc.deployment.StartupBuildSteps#addScope","started":"19:49:49.765","dependents":[297],"id":167,"thread":"build-28"},{"duration":0,"stepId":"io.quarkus.jdbc.postgresql.deployment.JDBCPostgreSQLProcessor#devDbHandler","started":"19:49:49.497","dependents":[290],"id":20,"thread":"build-8"},{"duration":0,"stepId":"io.quarkus.deployment.steps.MainClassBuildStep#mainClassBuildStep","started":"19:49:50.205","dependents":[],"id":235,"thread":"build-8"},{"duration":0,"stepId":"io.quarkus.resteasy.reactive.server.deployment.ResteasyReactiveProcessor#buildSetup","started":"19:49:49.743","dependents":[376],"id":123,"thread":"build-6"},{"duration":0,"stepId":"io.quarkus.arc.deployment.LifecycleEventsBuildStep#startupEvent","started":"19:49:53.421","dependents":[374,376],"id":373,"thread":"build-26"},{"duration":0,"stepId":"io.quarkus.hibernate.orm.deployment.HibernateOrmProcessor#registerHibernateOrmMetadataForCoreDialects","started":"19:49:49.610","dependents":[279],"id":50,"thread":"build-3"},{"duration":0,"stepId":"io.quarkus.resteasy.reactive.server.deployment.ResteasyReactiveDevModeProcessor#addAdditionalEndpointsExceptionMapper","started":"19:49:51.674","dependents":[376],"id":359,"thread":"build-28"},{"duration":0,"stepId":"io.quarkus.deployment.ConstructorPropertiesProcessor#build","started":"19:49:50.207","dependents":[375],"id":241,"thread":"build-9"},{"duration":0,"stepId":"io.quarkus.arc.deployment.StartupBuildSteps#unremovableBeans","started":"19:49:49.746","dependents":[328],"id":130,"thread":"build-16"},{"duration":0,"stepId":"io.quarkus.arc.deployment.ConfigBuildStep#registerConfigPropertiesBean","started":"19:49:50.627","dependents":[326],"id":311,"thread":"build-11"},{"duration":0,"stepId":"io.quarkus.vertx.core.deployment.VertxCoreProcessor#filterNettyHostsFileParsingWarn","started":"19:49:49.744","dependents":[152,289],"id":126,"thread":"build-20"},{"duration":0,"stepId":"io.quarkus.hibernate.orm.panache.deployment.PanacheHibernateResourceProcessor#featureBuildItem","started":"19:49:49.743","dependents":[376],"id":124,"thread":"build-15"},{"duration":0,"stepId":"io.quarkus.resteasy.reactive.server.deployment.ResteasyReactiveCDIProcessor#pathInterfaceImpls","started":"19:49:50.215","dependents":[291,301],"id":261,"thread":"build-7"},{"duration":0,"stepId":"io.quarkus.vertx.core.deployment.VertxCoreProcessor#overrideContextInternalInterfaceToAddSafeGuards","started":"19:49:49.606","dependents":[368],"id":47,"thread":"build-6"},{"duration":0,"stepId":"io.quarkus.arc.deployment.ArcProcessor#setupExecutor","started":"19:49:49.825","dependents":[376],"id":196,"thread":"build-22"},{"duration":0,"stepId":"io.quarkus.arc.deployment.ConfigBuildStep#generateConfigClasses","started":"19:49:50.206","dependents":[311,329,335,375,313],"id":236,"thread":"build-8"},{"duration":0,"stepId":"io.quarkus.arc.deployment.staticmethods.InterceptedStaticMethodsProcessor#processInterceptedStaticMethods","started":"19:49:50.631","dependents":[368,375,365],"id":319,"thread":"build-5"},{"duration":0,"stepId":"io.quarkus.reactive.datasource.deployment.ReactiveDataSourceProcessor#addQualifierAsBean","started":"19:49:49.739","dependents":[291,301],"id":112,"thread":"build-7"},{"duration":0,"stepId":"io.quarkus.resteasy.reactive.server.deployment.ResteasyReactiveScanningProcessor#scanForInterceptors","started":"19:49:50.215","dependents":[272],"id":265,"thread":"build-14"},{"duration":0,"stepId":"io.quarkus.resteasy.reactive.server.deployment.devconsole.ResteasyReactiveDevConsoleProcessor#collectAdditionalEndpoints","started":"19:49:51.674","dependents":[362],"id":358,"thread":"build-5"},{"duration":0,"stepId":"io.quarkus.vertx.http.deployment.VertxHttpProcessor#openSocket","started":"19:49:53.421","dependents":[375,376],"id":374,"thread":"build-22"},{"duration":0,"stepId":"io.quarkus.arc.deployment.AutoInjectFieldProcessor#annotationTransformer","started":"19:49:50.359","dependents":[301],"id":295,"thread":"build-14"},{"duration":0,"stepId":"io.quarkus.vertx.http.deployment.devmode.tests.TestsProcessor#toggleLiveReloadEnabled","started":"19:49:49.565","dependents":[370,309],"id":34,"thread":"build-8"},{"duration":0,"stepId":"io.quarkus.deployment.steps.ApplicationInfoBuildStep#create","started":"19:49:49.632","dependents":[376],"id":69,"thread":"build-5"},{"duration":0,"stepId":"io.quarkus.vertx.deployment.VertxProcessor#registerBean","started":"19:49:49.629","dependents":[291,301],"id":63,"thread":"build-7"},{"duration":0,"stepId":"io.quarkus.deployment.ExtensionLoader#booleanSupplierFactory","started":"19:49:49.628","dependents":[82],"id":60,"thread":"build-8"},{"duration":0,"stepId":"io.quarkus.deployment.logging.LoggingResourceProcessor#setUpDefaultLevels","started":"19:49:49.776","dependents":[307,289],"id":180,"thread":"build-21"},{"duration":0,"stepId":"io.quarkus.hibernate.orm.deployment.HibernateOrmProcessor#handleNativeImageImportSql","started":"19:49:50.312","dependents":[308],"id":283,"thread":"build-16"},{"duration":0,"stepId":"io.quarkus.resteasy.reactive.server.deployment.ObservabilityProcessor#integrateObservability","started":"19:49:49.768","dependents":[346],"id":171,"thread":"build-27"},{"duration":0,"stepId":"io.quarkus.hibernate.orm.deployment.HibernateLogFilterBuildStep#setupLogFilters","started":"19:49:49.746","dependents":[152,289],"id":131,"thread":"build-11"},{"duration":0,"stepId":"io.quarkus.deployment.pkg.steps.PackageTypeVerificationBuildStep#builtins","started":"19:49:49.630","dependents":[99],"id":65,"thread":"build-5"},{"duration":0,"stepId":"io.quarkus.resteasy.reactive.jackson.deployment.processor.ResteasyReactiveJacksonProcessor#feature","started":"19:49:49.744","dependents":[376],"id":127,"thread":"build-19"},{"duration":0,"stepId":"io.quarkus.hibernate.orm.deployment.HibernateOrmProcessor#warnOfSchemaProblems","started":"19:49:53.421","dependents":[376],"id":371,"thread":"build-8"},{"duration":0,"stepId":"io.quarkus.resteasy.reactive.common.deployment.ResteasyReactiveCommonProcessor#scanForIOInterceptors","started":"19:49:50.215","dependents":[272],"id":267,"thread":"build-1"},{"duration":0,"stepId":"io.quarkus.deployment.steps.DevServicesConfigBuildStep#deprecated","started":"19:49:49.773","dependents":[299],"id":175,"thread":"build-6"},{"duration":0,"stepId":"io.quarkus.hibernate.orm.deployment.HibernateOrmProcessor#hotDeploymentWatchedFiles","started":"19:49:49.744","dependents":[287],"id":128,"thread":"build-19"},{"duration":0,"stepId":"io.quarkus.jdbc.postgresql.deployment.PostgreSQLJDBCReflections#build","started":"19:49:49.747","dependents":[375],"id":133,"thread":"build-8"},{"duration":0,"stepId":"io.quarkus.deployment.steps.ReflectionDiagnosticProcessor#writeReflectionData","started":"19:49:53.422","dependents":[],"id":375,"thread":"build-26"},{"duration":0,"stepId":"io.quarkus.caffeine.deployment.CaffeineProcessor#cacheLoaders","started":"19:49:50.207","dependents":[375],"id":244,"thread":"build-17"},{"duration":0,"stepId":"io.quarkus.hibernate.orm.deployment.HibernateUserTypeProcessor#build","started":"19:49:50.203","dependents":[375],"id":228,"thread":"build-5"}],"started":"2022-07-31T19:49:49.468","buildTarget":"football_manager-1.0-SNAPSHOT"}